s3pathlib/__init__.py
s3pathlib/_version.py
s3pathlib/aws.py
s3pathlib/better_client/__init__.py
s3pathlib/better_client/api.py
s3pathlib/better_client/delete_object.py
s3pathlib/better_client/head_bucket.py
s3pathlib/better_client/head_object.py
s3pathlib/better_client/list_object_versions.py
s3pathlib/better_client/list_objects.py
s3pathlib/better_client/tagging.py
s3pathlib/better_client/upload.py
s3pathlib/compat.py
s3pathlib/constants.py
s3pathlib/content_type.py
s3pathlib/core/__init__.py
s3pathlib/core/attribute.py
s3pathlib/core/base.py
s3pathlib/core/bucket.py
s3pathlib/core/comparison.py
s3pathlib/core/copy.py
s3pathlib/core/delete.py
s3pathlib/core/exists.py
s3pathlib/core/filterable_property.py
s3pathlib/core/is_test.py
s3pathlib/core/iter_object_versions.py
s3pathlib/core/iter_objects.py
s3pathlib/core/joinpath.py
s3pathlib/core/metadata.py
s3pathlib/core/mutate.py
s3pathlib/core/opener.py
s3pathlib/core/relative.py
s3pathlib/core/resolve_s3_client.py
s3pathlib/core/rw.py
s3pathlib/core/s3path.py
s3pathlib/core/serde.py
s3pathlib/core/sync.py
s3pathlib/core/tagging.py
s3pathlib/core/upload.py
s3pathlib/core/uri.py
s3pathlib/exc.py
s3pathlib/marker.py
s3pathlib/metadata.py
s3pathlib/tag.py
s3pathlib/type.py
s3pathlib/utils.py
s3pathlib/validate.py
s3pathlib-2.3.6.dist-info/AUTHORS.rst
s3pathlib-2.3.6.dist-info/LICENSE
s3pathlib-2.3.6.dist-info/METADATA
s3pathlib-2.3.6.dist-info/NOTICE
s3pathlib-2.3.6.dist-info/WHEEL
s3pathlib-2.3.6.dist-info/RECORD
