Metadata-Version: 2.3
Name: s3pathlib
Version: 2.3.6
Summary: s3pathlib is the python package provides the Pythonic objective oriented programming (OOP) interface to manipulate AWS S3 object / directory. The api is similar to the pathlib standard library and very intuitive for human.
License: Apache-2.0
Author: Sanhe Hu, Jiazhen Zhu
Author-email: husanhe@email.com
Maintainer: Sanhe Hu, Jiazhen Zhu
Maintainer-email: husanhe@email.com
Requires-Python: >=3.9,<4.0
Classifier: License :: OSI Approved :: Apache Software License
Classifier: Programming Language :: Python :: 3
Classifier: Programming Language :: Python :: 3.9
Classifier: Programming Language :: Python :: 3.10
Classifier: Programming Language :: Python :: 3.11
Classifier: Programming Language :: Python :: 3.12
Classifier: Programming Language :: Python :: 3.13
Provides-Extra: auto
Provides-Extra: dev
Provides-Extra: doc
Provides-Extra: test
Requires-Dist: Sphinx (>=7.4.7,<8.0.0) ; extra == "doc"
Requires-Dist: boto3 (>=1.33.0,<2.0.0)
Requires-Dist: boto3-stubs[s3,sts] (>=1.33.0,<2.0.0) ; extra == "dev"
Requires-Dist: boto_session_manager (>=1.5.1,<2.0.0)
Requires-Dist: build (>=1.2.1,<2.0.0) ; extra == "dev"
Requires-Dist: decorator (>=5.0.5,<6.0.0) ; extra == "test"
Requires-Dist: docfly (==3.0.0) ; extra == "doc"
Requires-Dist: func_args (>=0.1.1,<2.0.0)
Requires-Dist: furo (==2024.8.6) ; extra == "doc"
Requires-Dist: ipython (>=8.18.1,<8.19.0) ; extra == "doc"
Requires-Dist: iterproxy (>=0.3.1,<1.0.0)
Requires-Dist: moto (>=5.0.28,<6.0.0) ; extra == "test"
Requires-Dist: nbsphinx (>=0.8.12,<1.0.0) ; extra == "doc"
Requires-Dist: pathlib_mate (>=1.0.1,<2.0.0)
Requires-Dist: pygments (>=2.18.0,<3.0.0) ; extra == "doc"
Requires-Dist: pytest (>=8.2.2,<9.0.0) ; extra == "test"
Requires-Dist: pytest-cov (>=6.0.0,<7.0.0) ; extra == "test"
Requires-Dist: rich (>=13.8.1,<14.0.0) ; extra == "dev"
Requires-Dist: rich (>=13.8.1,<14.0.0) ; extra == "test"
Requires-Dist: rstobj (==1.2.1) ; extra == "doc"
Requires-Dist: smart_open (>=5.1.0,<8.0.0)
Requires-Dist: sphinx-copybutton (>=0.5.2,<1.0.0) ; extra == "doc"
Requires-Dist: sphinx-design (>=0.6.1,<1.0.0) ; extra == "doc"
Requires-Dist: sphinx-jinja (>=2.0.2,<3.0.0) ; extra == "doc"
Requires-Dist: twine (>=6.0.0,<7.0.0) ; extra == "dev"
Requires-Dist: wheel (>=0.45.0,<1.0.0) ; extra == "dev"
Project-URL: Changelog, https://github.com/MacHu-GWU/s3pathlib-project/blob/main/release-history.rst
Project-URL: Documentation, https://s3pathlib.readthedocs.io/en/latest/
Project-URL: Download, https://pypi.org/pypi/s3pathlib#files
Project-URL: Homepage, https://github.com/MacHu-GWU/s3pathlib-project
Project-URL: Issues, https://github.com/MacHu-GWU/s3pathlib-project/issues
Project-URL: Repository, https://github.com/MacHu-GWU/s3pathlib-project
